ratpmetro/__about__.py
ratpmetro/__init__.py
ratpmetro/main.py
ratpmetro-0.0.2.dist-info/LICENSE
ratpmetro-0.0.2.dist-info/METADATA
ratpmetro-0.0.2.dist-info/WHEEL
ratpmetro-0.0.2.dist-info/top_level.txt
ratpmetro-0.0.2.dist-info/RECORD
