Metadata-Version: 2.1
Name: ratpmetro
Version: 0.0.2
Summary: Incident analysis of Paris RATP metro lines
Home-page: https://github.com/tianyikillua/ratpmetro
Author: Tianyi Li
Author-email: tianyikillua@gmail.com
License: License :: OSI Approved :: MIT License
Platform: UNKNOWN
Classifier: License :: OSI Approved :: MIT License
Classifier: Development Status :: 4 - Beta
Classifier: Operating System :: OS Independent
Classifier: Programming Language :: Python :: 3
Requires-Dist: pandas
Requires-Dist: numpy
Requires-Dist: tweepy
Requires-Dist: matplotlib
